hydrotools/nwis_client/__init__.py
hydrotools/nwis_client/_utilities.py
hydrotools/nwis_client/_version.py
hydrotools/nwis_client/cli.py
hydrotools/nwis_client/iv.py
hydrotools_nwis_client-4.1.0.dist-info/licenses/LICENSE
hydrotools_nwis_client-4.1.0.dist-info/licenses/NOTICE
hydrotools_nwis_client-4.1.0.dist-info/METADATA
hydrotools_nwis_client-4.1.0.dist-info/WHEEL
hydrotools_nwis_client-4.1.0.dist-info/entry_points.txt
hydrotools_nwis_client-4.1.0.dist-info/top_level.txt
hydrotools_nwis_client-4.1.0.dist-info/RECORD
