Metadata-Version: 2.4
Name: hydrotools.nwis_client
Version: 4.1.0
Summary: A convenient interface to the USGS NWIS Instantaneous Values (IV) REST Service API.
Author-email: Austin Raney <aaraney@protonmail.com>, "Jason A. Regina" <jason.regina@noaa.gov>
License: 
Project-URL: Homepage, https://github.com/NOAA-OWP/hydrotools
Project-URL: Documentation, https://noaa-owp.github.io/hydrotools/hydrotools.nwis_client.html
Project-URL: Repository, https://github.com/NOAA-OWP/hydrotools/tree/main/python/nwis_client
Project-URL: Bug Tracker, https://github.com/NOAA-OWP/hydrotools/issues
Classifier: Development Status :: 5 - Production/Stable
Classifier: Intended Audience :: Education
Classifier: Intended Audience :: Science/Research
Classifier: License :: OSI Approved :: Apache Software License
Classifier: Programming Language :: Python :: 3.9
Classifier: Programming Language :: Python :: 3.10
Classifier: Programming Language :: Python :: 3.11
Classifier: Programming Language :: Python :: 3.12
Classifier: Topic :: Scientific/Engineering :: Hydrology
Classifier: Operating System :: OS Independent
Requires-Python: >=3.9
License-File: LICENSE
License-File: NOTICE
Requires-Dist: pandas
Requires-Dist: numpy
Requires-Dist: hydrotools._restclient>=4.1.0
Requires-Dist: aiohttp
Requires-Dist: click
Provides-Extra: develop
Requires-Dist: pytest; extra == "develop"
Requires-Dist: pytest-aiohttp; extra == "develop"
Dynamic: license-file
